MANIFEST.in
readme.md
setup.py
recad/__init__.py
recad/default.py
recad/main.py
recad/utils.py
recad.egg-info/PKG-INFO
recad.egg-info/SOURCES.txt
recad.egg-info/dependency_links.txt
recad.egg-info/entry_points.txt
recad.egg-info/requires.txt
recad.egg-info/top_level.txt
recad/dataset/__init__.py
recad/dataset/base.py
recad/dataset/explicit.py
recad/dataset/implicit.py
recad/model/__init__.py
recad/model/base.py
recad/model/attacker/__init__.py
recad/model/attacker/aia.py
recad/model/attacker/aush.py
recad/model/attacker/aushplus.py
recad/model/attacker/base.py
recad/model/attacker/heuristic.py
recad/model/victim/__init__.py
recad/model/victim/base.py
recad/model/victim/lightgcn.py
recad/model/victim/mf.py
recad/model/victim/ncf.py
recad/workflow/__init__.py
recad/workflow/base.py
recad/workflow/normal.py