Metadata-Version: 2.1
Name: recad
Version: 0.0.2
Summary: A unified framework for recommender system attacking
Home-page: https://github.com/gusye1234/recad
Author: JianbaiYe
License: GPLv3
Platform: UNKNOWN
Requires-Python: >=3.6
